odoo/addons/account_move_change_company/README.rst
odoo/addons/account_move_change_company/__init__.py
odoo/addons/account_move_change_company/__manifest__.py
odoo/addons/account_move_change_company/i18n/account_move_change_company.pot
odoo/addons/account_move_change_company/i18n/es.po
odoo/addons/account_move_change_company/i18n/it.po
odoo/addons/account_move_change_company/models/__init__.py
odoo/addons/account_move_change_company/models/account_move.py
odoo/addons/account_move_change_company/readme/CONTRIBUTORS.rst
odoo/addons/account_move_change_company/readme/DESCRIPTION.rst
odoo/addons/account_move_change_company/static/description/icon.png
odoo/addons/account_move_change_company/static/description/index.html
odoo/addons/account_move_change_company/tests/__init__.py
odoo/addons/account_move_change_company/tests/test_change_company.py
odoo/addons/account_move_change_company/views/account_move.xml
odoo_addon_account_move_change_company-16.0.1.0.0.5.dist-info/METADATA
odoo_addon_account_move_change_company-16.0.1.0.0.5.dist-info/WHEEL
odoo_addon_account_move_change_company-16.0.1.0.0.5.dist-info/top_level.txt
odoo_addon_account_move_change_company-16.0.1.0.0.5.dist-info/RECORD
